{
  "Data Communication & Physical Layer": [
    "data communication components",
    "representation of data",
    "data flow",
    "network topologies",
    "protocols and standards",
    "iso-osi reference model",
    "tcp/ip model",
    "comparison of osi and tcp/ip",
    "layered network architecture",
    "baseband transmission",
    "broadband transmission",
    "transmission impairments",
    "attenuation",
    "noise",
    "distortion",
    "guided media",
    "twisted pair cable",
    "coaxial cable",
    "fiber optic cable",
    "wireless media",
    "microwave",
    "satellite",
    "wimax",
    "bluetooth",
    "wired lan",
    "wireless lan",
    "virtual lan",
    "vlan",
    "multiplexing techniques",
    "frequency division multiplexing",
    "fdm",
    "time division multiplexing",
    "tdm",
    "inverse tdm",
    "wavelength division multiplexing",
    "wdm",
    "guard bands",
    "spread spectrum",
    "frequency hopping spread spectrum",
    "fhss",
    "direct sequence spread spectrum",
    "dsss",
    "line coding",
    "signaling",
    "bit rate vs baud rate",
    "signaling rate",
    "pulse rate",
    "encoding techniques",
    "nrz-l",
    "nrz-i",
    "rz",
    "manchester encoding",
    "differential manchester encoding",
    "qpsk",
    "qam",
    "fsk",
    "channel capacity",
    "nyquist theorem",
    "nyquist sampling rate",
    "shannon theorem",
    "shannon's theorem",
    "shannon’s theorem",
    "sampling",
    "bandwidth",
    "bandwidth calculation"
  ],
  "Data Link Layer & Medium Access Sublayer": [
    "framing concepts",
    "bit stuffing",
    "byte stuffing",
    "character stuffing",
    "parity check",
    "1d parity",
    "2d parity",
    "checksum",
    "cyclic redundancy check",
    "crc",
    "error correction",
    "hamming code",
    "hamming distance",
    "single-bit errors",
    "burst errors",
    "stop-and-wait protocol",
    "sliding window protocol",
    "stop-and-wait arq",
    "acknowledgement numbering",
    "efficiency calculation",
    "go-back-n arq",
    "go-back-n",
    "window size",
    "nak",
    "negative acknowledgement",
    "channel utilization",
    "selective repeat arq",
    "selective repeat",
    "sender window",
    "receiver window",
    "piggybacking",
    "random access protocols",
    "pure aloha",
    "slotted aloha",
    "csma",
    "csma/cd",
    "csma/ca",
    "controlled access protocols",
    "polling",
    "token passing",
    "ethernet",
    "ieee 802.3",
    "frame format",
    "minimum frame length",
    "hdlc",
    "high-level data link control",
    "bit-oriented protocol",
    "data transparency",
    "circuit switching",
    "packet switching",
    "message switching",
    "virtual circuit"
  ],
  "Network Layer": [
    "logical addressing",
    "ip addressing",
    "physical addressing",
    "mac addressing",
    "ipv4",
    "classful addressing",
    "subnetting",
    "supernetting",
    "cidr",
    "classless inter-domain routing",
    "nat",
    "network address translation",
    "ipv6",
    "ipv6 header",
    "ipv6 header format",
    "advantages of ipv6",
    "arp",
    "address resolution protocol",
    "rarp",
    "reverse address resolution protocol",
    "bootp",
    "bootstrap protocol",
    "dhcp",
    "dynamic host configuration protocol",
    "static routing",
    "dynamic routing",
    "distance vector routing",
    "rip",
    "routing information protocol",
    "count-to-infinity",
    "count-to-infinity problem",
    "split horizon",
    "link state routing",
    "ospf",
    "open shortest path first",
    "dijkstra algorithm",
    "dijkstra's algorithm",
    "dijkstra’s algorithm",
    "bgp",
    "border gateway protocol",
    "inter-as routing",
    "intra-as routing",
    "autonomous systems",
    "packet delivery",
    "packet forwarding",
    "icmp",
    "internet control message protocol",
    "ttl",
    "time to live",
    "ip datagram",
    "ip datagram format",
    "vpn",
    "virtual private network",
    "leaky bucket",
    "leaky bucket algorithm",
    "token bucket",
    "token bucket algorithm",
    "quality of service",
    "qos"
  ],
  "Transport Layer": [
    "process-to-process communication",
    "transmission control protocol",
    "tcp",
    "connection-oriented service",
    "tcp header",
    "three-way handshake",
    "congestion control",
    "user datagram protocol",
    "udp",
    "connectionless service",
    "sctp",
    "stream control transmission protocol",
    "tcp congestion avoidance",
    "slow start",
    "additive increase multiplicative decrease",
    "aimd",
    "open-loop congestion control",
    "closed-loop congestion control"
  ],
  "Application Layer": [
    "domain name system",
    "dns",
    "recursive queries",
    "iterative queries",
    "dynamic dns",
    "ddns",
    "http",
    "hypertext transfer protocol",
    "https",
    "file transfer protocol",
    "ftp",
    "telnet",
    "remote login",
    "electronic mail",
    "email",
    "smtp",
    "simple mail transfer protocol",
    "pop3",
    "post office protocol",
    "imap",
    "internet message access protocol",
    "snmp",
    "simple network management protocol",
    "world wide web",
    "www"
  ],
  "Network Security": [
    "cryptography",
    "cryptography basics",
    "symmetric encryption",
    "asymmetric encryption",
    "public key encryption",
    "rsa",
    "digital signature",
    "key management",
    "key distribution centre",
    "kdc",
    "key agreement",
    "key transport",
    "authentication",
    "integrity",
    "non-repudiation",
    "firewalls",
    "firewall",
    "proxy servers",
    "proxy"
  ],
  "Advanced / Supplementary Topics": [
    "wireless networks",
    "ieee 802.11",
    "wi-fi",
    "bluetooth",
    "dqdb",
    "distributed queue dual bus",
    "fddi",
    "fiber distributed data interface",
    "wan technologies",
    "isdn",
    "integrated services digital network",
    "atm",
    "asynchronous transfer mode",
    "frame relay",
    "cdma",
    "code division multiple access",
    "intranet",
    "internet"
  ]
}